LICENSE
README.md
setup.cfg
setup.py
softpy/__init__.py
softpy.egg-info/PKG-INFO
softpy.egg-info/SOURCES.txt
softpy.egg-info/dependency_links.txt
softpy.egg-info/requires.txt
softpy.egg-info/top_level.txt
softpy/evolutionary/__init__.py
softpy/evolutionary/candidate.py
softpy/evolutionary/genetic.py
softpy/evolutionary/selection.py
softpy/evolutionary/singlestate.py
softpy/fuzzy/__init__.py
softpy/fuzzy/clustering.py
softpy/fuzzy/fuzzy_control.py
softpy/fuzzy/fuzzy_operation.py
softpy/fuzzy/fuzzy_partition.py
softpy/fuzzy/fuzzy_rule.py
softpy/fuzzy/fuzzyset.py
softpy/fuzzy/knowledge_base.py
softpy/fuzzy/memberships_function.py
softpy/fuzzy/operations.py