Metadata-Version: 2.1
Name: softpy
Version: 0.0.6
Summary: A package for soft computing in Python.
Home-page: https://pypi.org/project/softpy/
Author: Andrea Campagner
Author-email: onyris93@gmail.com
License: LICENSE.txt
Requires-Python: >3.8.0
License-File: LICENSE
Requires-Dist: numpy>=1.24.0
Requires-Dist: scipy>=1.11.0
